sotiRPA/__init__.py
sotiRPA/win.cp38-win_amd64.pyd
sotiRPA/win.pyi
sotiRPA/_uiautomation/__init__.py
sotiRPA/_uiautomation/uiautomation.py
sotiRPA/_uiautomation/version.py
sotiRPA/utils/Action.py
sotiRPA/utils/__init__.py
sotiRPA/utils/tools.py
sotirpa-0.0.5.dist-info/METADATA
sotirpa-0.0.5.dist-info/WHEEL
sotirpa-0.0.5.dist-info/top_level.txt
sotirpa-0.0.5.dist-info/RECORD
