Metadata-Version: 2.1
Name: sotiRPA
Version: 0.0.5
Summary: sotiRPA：手替，表示能够代替手去工作
Author-email: yangsheng <1453408846@qq.com>
License: Apache 2.0
Project-URL: text, https://gitee.com/Gitee1453408846/rpa-lib
Keywords: local laplace filter,local-laplace-filter,computer vision,tone mapping,image process
Classifier: Intended Audience :: Developers
Classifier: Operating System :: OS Independent
Classifier: Programming Language :: Python :: 3
Requires-Python: >=3.5
